{"state_name":["Mississippi"],"bad_neighbor_count":[29],"nn_abundance":[857],"state_nn_species_count":[17],"species_list":[{"name":"Callicarpa dichotoma","cnt":1,"tsn":32145},{"name":"Clerodendrum bungei","cnt":15,"tsn":32158},{"name":"Clerodendrum trichotomum","cnt":1,"tsn":501588},{"name":"Clerodendrum trichotomum ferrugineum","cnt":1,"tsn":531017},{"name":"Galeopsis bifida","cnt":272,"tsn":32496},{"name":"Galeopsis ladanum","cnt":1,"tsn":32497},{"name":"Galeopsis tetrahit","cnt":320,"tsn":32499},{"name":"Galeopsis tetrahit tetrahit","cnt":2,"tsn":528208},{"name":"Lamium album","cnt":17,"tsn":32538},{"name":"Lamium maculatum","cnt":2,"tsn":32541},{"name":"Lamium purpureum incisum","cnt":5,"tsn":528670},{"name":"Leonurus sibiricus","cnt":23,"tsn":32550},{"name":"Lycopus europaeus","cnt":1,"tsn":32260},{"name":"Marrubium vulgare","cnt":20,"tsn":32561},{"name":"Mentha gracilis","cnt":1,"tsn":503751},{"name":"Mentha suaveolens","cnt":2,"tsn":503753},{"name":"Mosla dianthera","cnt":14,"tsn":32621},{"name":"Ocimum basilicum","cnt":2,"tsn":32627},{"name":"Perilla frutescens frutescens","cnt":97,"tsn":529521},{"name":"Salvia officinalis","cnt":3,"tsn":32729},{"name":"Salvia verbenaca","cnt":1,"tsn":832901},{"name":"Scutellaria racemosa","cnt":35,"tsn":196146},{"name":"Stachys byzantina","cnt":2,"tsn":505350},{"name":"Thymus praecox","cnt":1,"tsn":32821},{"name":"Thymus praecox arcticus","cnt":1,"tsn":524754},{"name":"Vitex negundo","cnt":8,"tsn":32222},{"name":"Vitex negundo intermedia","cnt":3,"tsn":530846},{"name":"Vitex negundo negundo","cnt":3,"tsn":530847},{"name":"Vitex rotundifolia","cnt":3,"tsn":505725}]}
