{"state_name":["California"],"bad_neighbor_count":[23],"nn_abundance":[99],"state_nn_species_count":[167],"species_list":[{"name":"Acacia auriculiformis","cnt":1,"tsn":182096},{"name":"Astragalus falcatus","cnt":4,"tsn":25513},{"name":"Astragalus hamosus","cnt":1,"tsn":506836},{"name":"Chamaecrista absus","cnt":2,"tsn":501378},{"name":"Chamaecrista absus meonandra","cnt":2,"tsn":527264},{"name":"Cytisus praecox","cnt":1,"tsn":506933},{"name":"Desmodium intortum","cnt":1,"tsn":25805},{"name":"Macroptilium gibbosifolium","cnt":16,"tsn":503646},{"name":"Medicago sativa falcata","cnt":5,"tsn":524302},{"name":"Medicago sativa sativa","cnt":32,"tsn":524303},{"name":"Medicago turbinata","cnt":3,"tsn":503729},{"name":"Ononis arvensis","cnt":2,"tsn":504024},{"name":"Ononis repens","cnt":1,"tsn":26812},{"name":"Ornithopus compressus","cnt":7,"tsn":565343},{"name":"Ornithopus perpusillus","cnt":6,"tsn":504060},{"name":"Prosopis alpataco","cnt":3,"tsn":565983},{"name":"Prosopis argentina","cnt":1,"tsn":565984},{"name":"Prosopis laevigata","cnt":1,"tsn":26880},{"name":"Pueraria montana","cnt":3,"tsn":504683},{"name":"Pueraria montana lobata","cnt":4,"tsn":529930},{"name":"Trifolium echinatum","cnt":1,"tsn":507213},{"name":"Trifolium michelianum","cnt":1,"tsn":506276},{"name":"Vicia narbonensis","cnt":1,"tsn":26351}]}
