{"state_name":["Massachusetts"],"bad_neighbor_count":[19],"nn_abundance":[171],"state_nn_species_count":[14],"species_list":[{"name":"Acridotheres cristatellus","cnt":1,"tsn":179642},{"name":"Agapornis roseicollis","cnt":73,"tsn":177626},{"name":"Aix galericulata","cnt":3,"tsn":175123},{"name":"Alauda arvensis","cnt":1,"tsn":178398},{"name":"Alectoris chukar","cnt":7,"tsn":175908},{"name":"Amazona viridigenalis","cnt":1,"tsn":177806},{"name":"Anas falcata","cnt":1,"tsn":175080},{"name":"Anas hottentota","cnt":1,"tsn":175105},{"name":"Anser anser","cnt":34,"tsn":175028},{"name":"Geopelia cuneata","cnt":1,"tsn":177194},{"name":"Gracula religiosa","cnt":5,"tsn":179652},{"name":"Lonchura malacca","cnt":9,"tsn":179618},{"name":"Melopsittacus undulatus","cnt":9,"tsn":177597},{"name":"Nandayus nenday","cnt":5,"tsn":177693},{"name":"Numida meleagris","cnt":6,"tsn":176126},{"name":"Nymphicus hollandicus","cnt":3,"tsn":177497},{"name":"Psittacula krameri","cnt":2,"tsn":177650},{"name":"Streptopelia chinensis","cnt":1,"tsn":177134},{"name":"Taeniopygia guttata","cnt":8,"tsn":563276}]}
