{"state_name":["North_Dakota"],"species_count":[13],"nn_abundance":[8025],"species_list":[{"name":"Aix galericulata","cnt":2,"tsn":175123},{"name":"Anas hottentota","cnt":14,"tsn":175105},{"name":"Anser anser","cnt":1,"tsn":175028},{"name":"Anser cygnoides","cnt":1,"tsn":175032},{"name":"Callonetta leucophrys","cnt":12,"tsn":553914},{"name":"Cygnus atratus","cnt":2,"tsn":553906},{"name":"Geopelia cuneata","cnt":2,"tsn":177194},{"name":"Lonchura malacca","cnt":10,"tsn":179618},{"name":"Lonchura punctulata","cnt":13,"tsn":179619},{"name":"Passer montanus","cnt":7958,"tsn":179630},{"name":"Pavo cristatus","cnt":8,"tsn":176113},{"name":"Tadorna tadorna","cnt":1,"tsn":175055},{"name":"Taeniopygia guttata","cnt":1,"tsn":563276}]}
