{"state_name":["New_Jersey"],"bad_neighbor_count":[87],"nn_abundance":[442],"state_nn_species_count":[84],"species_list":[{"name":"Aegilops crassa","cnt":2,"tsn":182535},{"name":"Aegilops cylindrica","cnt":14,"tsn":182536},{"name":"Aegilops geniculata","cnt":1,"tsn":182539},{"name":"Aegilops tauschii","cnt":2,"tsn":565607},{"name":"Aegilops triuncialis","cnt":2,"tsn":182540},{"name":"Agropyron cristatum","cnt":5,"tsn":40371},{"name":"Agropyron desertorum","cnt":2,"tsn":40372},{"name":"Alopecurus creticus","cnt":1,"tsn":40441},{"name":"Alopecurus geniculatus geniculatus","cnt":8,"tsn":182516},{"name":"Alopecurus rendlei","cnt":3,"tsn":182518},{"name":"Ammophila arenaria","cnt":2,"tsn":40449},{"name":"Ampelodesmos mauritanicus","cnt":1,"tsn":782167},{"name":"Avena strigosa","cnt":1,"tsn":193431},{"name":"Bothriochloa ischaemum songarica","cnt":1,"tsn":526948},{"name":"Brachypodium sylvaticum","cnt":20,"tsn":41331},{"name":"Briza media","cnt":12,"tsn":41530},{"name":"Briza minor","cnt":2,"tsn":41531},{"name":"Bromus briziformis","cnt":3,"tsn":40495},{"name":"Bromus erectus","cnt":8,"tsn":40483},{"name":"Bromus lanceolatus","cnt":1,"tsn":501072},{"name":"Bromus lepidus","cnt":1,"tsn":501073},{"name":"Bromus scoparius","cnt":1,"tsn":40488},{"name":"Catapodium rigidum","cnt":1,"tsn":41543},{"name":"Cenchrus biflorus","cnt":1,"tsn":40572},{"name":"Cenchrus purpureus","cnt":1,"tsn":796726},{"name":"Cenchrus setaceus","cnt":1,"tsn":796732},{"name":"Coix lacryma-jobi","cnt":4,"tsn":41586},{"name":"Corynephorus canescens","cnt":14,"tsn":41599},{"name":"Crypsis alopecuroides","cnt":1,"tsn":41603},{"name":"Dasypyrum villosum","cnt":1,"tsn":193450},{"name":"Digitaria violascens","cnt":1,"tsn":502065},{"name":"Echinochloa colona","cnt":1,"tsn":40670},{"name":"Echinochloa frumentacea","cnt":27,"tsn":502211},{"name":"Eragrostis tef","cnt":1,"tsn":40738},{"name":"Eremopyrum bonaepartis","cnt":1,"tsn":502350},{"name":"Eremopyrum orientale","cnt":1,"tsn":502351},{"name":"Eremopyrum triticeum","cnt":1,"tsn":41717},{"name":"Eriochloa villosa","cnt":1,"tsn":41723},{"name":"Festuca filiformis","cnt":88,"tsn":565187},{"name":"Festuca heterophylla","cnt":12,"tsn":502606},{"name":"Glyceria declinata","cnt":1,"tsn":40835},{"name":"Glyceria maxima","cnt":5,"tsn":40846},{"name":"Hakonechloa macra","cnt":3,"tsn":783523},{"name":"Hemarthria altissima","cnt":2,"tsn":41760},{"name":"Holcus mollis","cnt":7,"tsn":41774},{"name":"Hordeum marinum","cnt":2,"tsn":40880},{"name":"Hordeum marinum gussoneanum","cnt":4,"tsn":797384},{"name":"Hordeum murinum murinum","cnt":1,"tsn":524162},{"name":"Lamarckia aurea","cnt":1,"tsn":41811},{"name":"Leymus arenarius","cnt":2,"tsn":503432},{"name":"Lolium","cnt":4,"tsn":40891},{"name":"Lolium persicum","cnt":3,"tsn":40895},{"name":"Melica altissima","cnt":1,"tsn":41843},{"name":"Mibora minima","cnt":1,"tsn":41865},{"name":"Miscanthus floridulus","cnt":1,"tsn":41871},{"name":"Miscanthus sacchariflorus","cnt":10,"tsn":503854},{"name":"Nardus stricta","cnt":6,"tsn":41952},{"name":"Oryza sativa","cnt":2,"tsn":41976},{"name":"Panicum bisulcatum","cnt":1,"tsn":504099},{"name":"Paspalum dilatatum","cnt":1,"tsn":40997},{"name":"Phalaris paradoxa","cnt":2,"tsn":41338},{"name":"Phleum arenarium","cnt":1,"tsn":41064},{"name":"Phleum paniculatum","cnt":1,"tsn":41066},{"name":"Phleum subulatum","cnt":1,"tsn":41067},{"name":"Phyllostachys aurea","cnt":1,"tsn":42023},{"name":"Phyllostachys aureosulcata","cnt":10,"tsn":504356},{"name":"Phyllostachys flexuosa","cnt":2,"tsn":504358},{"name":"Piptatherum miliaceum","cnt":1,"tsn":504407},{"name":"Poa chaixii","cnt":3,"tsn":41117},{"name":"Polypogon monspeliensis","cnt":9,"tsn":41171},{"name":"Puccinellia distans distans","cnt":28,"tsn":802275},{"name":"Puccinellia rupestris","cnt":5,"tsn":41223},{"name":"Rostraria cristata","cnt":2,"tsn":504835},{"name":"Schedonorus arundinaceus","cnt":27,"tsn":784875},{"name":"Schedonorus giganteus","cnt":2,"tsn":784876},{"name":"Sclerochloa dura","cnt":4,"tsn":42081},{"name":"Setaria adhaerens","cnt":1,"tsn":521410},{"name":"Setaria verticilliformis","cnt":12,"tsn":795068},{"name":"Sporobolus indicus","cnt":5,"tsn":42140},{"name":"Taeniatherum caput-medusae","cnt":2,"tsn":42203},{"name":"Thinopyrum pycnanthum","cnt":2,"tsn":565567},{"name":"Tragus berteronianus","cnt":1,"tsn":42216},{"name":"Trisetum flavescens","cnt":4,"tsn":41304},{"name":"Triticum turgidum","cnt":1,"tsn":42245},{"name":"Vulpia bromoides","cnt":4,"tsn":42261},{"name":"Vulpia ciliata","cnt":1,"tsn":505733},{"name":"Zoysia japonica","cnt":1,"tsn":42273}]}
