{"state_name":["Maryland"],"species_count":[707],"nn_abundance":[5639],"species_list":[{"name":"Acanthospermum australe","cnt":7,"tsn":36445},{"name":"Acanthospermum hispidum","cnt":1,"tsn":36446},{"name":"Achillea ptarmica","cnt":8,"tsn":35429},{"name":"Achyranthes japonica","cnt":2,"tsn":181937},{"name":"Actinidia chinensis","cnt":1,"tsn":506775},{"name":"Actinidia polygama","cnt":1,"tsn":506776},{"name":"Adiantum hispidulum","cnt":2,"tsn":17327},{"name":"Aegilops cylindrica","cnt":14,"tsn":182536},{"name":"Aegilops neglecta","cnt":3,"tsn":782096},{"name":"Aegilops tauschii","cnt":4,"tsn":565607},{"name":"Aethusa cynapium","cnt":11,"tsn":29569},{"name":"Aglaonema commutatum","cnt":2,"tsn":182565},{"name":"Aira caryophyllea caryophyllea","cnt":40,"tsn":798212},{"name":"Alisma plantago-aquatica","cnt":5,"tsn":38894},{"name":"Allium ampeloprasum","cnt":8,"tsn":42708},{"name":"Allium oleraceum","cnt":5,"tsn":42689},{"name":"Allium porrum","cnt":1,"tsn":42659},{"name":"Allium sativum","cnt":29,"tsn":42652},{"name":"Allium schoenoprasum","cnt":8,"tsn":42636},{"name":"Allium tuberosum","cnt":1,"tsn":506484},{"name":"Alnus cordata","cnt":2,"tsn":845148},{"name":"Alopecurus creticus","cnt":1,"tsn":40441},{"name":"Alopecurus geniculatus geniculatus","cnt":7,"tsn":182516},{"name":"Alopecurus rendlei","cnt":3,"tsn":182518},{"name":"Alternanthera ficoidea","cnt":1,"tsn":181946},{"name":"Alternanthera paronychioides","cnt":1,"tsn":822837},{"name":"Alternanthera philoxeroides","cnt":8,"tsn":20770},{"name":"Althaea cannabina","cnt":1,"tsn":181984},{"name":"Althaea hirsuta","cnt":2,"tsn":181985},{"name":"Althaea officinalis","cnt":17,"tsn":21610},{"name":"Ammi visnaga","cnt":1,"tsn":29578},{"name":"Ammophila arenaria","cnt":1,"tsn":40449},{"name":"Anacyclus clavatus","cnt":1,"tsn":780180},{"name":"Anagallis monelli","cnt":1,"tsn":182018},{"name":"Anchusa azurea","cnt":4,"tsn":31715},{"name":"Anchusa officinalis","cnt":3,"tsn":31718},{"name":"Anemone blanda","cnt":1,"tsn":506830},{"name":"Anredera cordifolia","cnt":2,"tsn":181920},{"name":"Anthoxanthum aristatum","cnt":13,"tsn":41394},{"name":"Anthoxanthum odoratum odoratum","cnt":182,"tsn":185294},{"name":"Anthriscus caucalis","cnt":2,"tsn":29586},{"name":"Anthriscus cerefolium","cnt":4,"tsn":29587},{"name":"Anthyllis vulneraria","cnt":2,"tsn":26461},{"name":"Antigonon leptopus","cnt":1,"tsn":20994},{"name":"Apera spica-venti","cnt":6,"tsn":41399},{"name":"Aphanes microcarpa","cnt":30,"tsn":184594},{"name":"Apium graveolens dulce","cnt":6,"tsn":182185},{"name":"Arachniodes simplicior","cnt":1,"tsn":184048},{"name":"Aralia elata","cnt":6,"tsn":184745},{"name":"Arctium lappa","cnt":22,"tsn":36545},{"name":"Arctotis stoechadifolia","cnt":2,"tsn":36551},{"name":"Argyreia nervosa","cnt":1,"tsn":30824},{"name":"Arnoseris minima","cnt":1,"tsn":36591},{"name":"Artemisia pontica","cnt":7,"tsn":35487},{"name":"Arum italicum","cnt":3,"tsn":42544},{"name":"Aruncus dioicus vulgaris","cnt":1,"tsn":184621},{"name":"Asparagus densiflorus","cnt":3,"tsn":193452},{"name":"Asperugo procumbens","cnt":4,"tsn":31723},{"name":"Asphodelus fistulosus","cnt":1,"tsn":42788},{"name":"Aster tataricus","cnt":20,"tsn":35664},{"name":"Astilbe japonica","cnt":2,"tsn":24307},{"name":"Atriplex littoralis","cnt":5,"tsn":565019},{"name":"Atriplex tatarica","cnt":1,"tsn":20569},{"name":"Aucuba japonica","cnt":4,"tsn":565023},{"name":"Avena strigosa","cnt":1,"tsn":193431},{"name":"Ballota nigra nigra","cnt":1,"tsn":32457},{"name":"Berberis vulgaris","cnt":75,"tsn":18837},{"name":"Beta vulgaris","cnt":15,"tsn":20681},{"name":"Betula pubescens","cnt":19,"tsn":183543},{"name":"Bixa orellana","cnt":2,"tsn":22251},{"name":"Boehmeria nivea","cnt":4,"tsn":19122},{"name":"Bonnemaisonia hamifera","cnt":2,"tsn":11779},{"name":"Borago officinalis","cnt":10,"tsn":31727},{"name":"Brachypodium sylvaticum","cnt":1,"tsn":41331},{"name":"Briza media","cnt":3,"tsn":41530},{"name":"Bromus diandrus rigidus","cnt":4,"tsn":798287},{"name":"Bromus erectus","cnt":9,"tsn":40483},{"name":"Bromus hordeaceus pseudothominei","cnt":2,"tsn":797311},{"name":"Bromus lanceolatus","cnt":1,"tsn":501072},{"name":"Bromus ramosus","cnt":1,"tsn":501076},{"name":"Bromus squarrosus","cnt":1,"tsn":40489},{"name":"Browallia americana","cnt":4,"tsn":30636},{"name":"Buddleja lindleyana","cnt":2,"tsn":29915},{"name":"Bunias orientalis","cnt":3,"tsn":23067},{"name":"Bupleurum odontites","cnt":1,"tsn":501096},{"name":"Butomus umbellatus","cnt":3,"tsn":38886},{"name":"Caladium bicolor","cnt":3,"tsn":42565},{"name":"Calamagrostis epigeios","cnt":7,"tsn":40536},{"name":"Callicarpa dichotoma","cnt":3,"tsn":32145},{"name":"Callisia fragrans","cnt":3,"tsn":39136},{"name":"Calluna vulgaris","cnt":2,"tsn":23634},{"name":"Calystegia hederacea","cnt":22,"tsn":501165},{"name":"Camelina sativa","cnt":20,"tsn":22600},{"name":"Camellia japonica","cnt":4,"tsn":506117},{"name":"Campanula glomerata","cnt":2,"tsn":34485},{"name":"Campanula latifolia","cnt":2,"tsn":34487},{"name":"Campanula persicifolia","cnt":4,"tsn":34491},{"name":"Campanula trachelium","cnt":1,"tsn":34501},{"name":"Canavalia ensiformis","cnt":1,"tsn":501179},{"name":"Cannabis sativa sativa","cnt":31,"tsn":566609},{"name":"Caragana arborescens","cnt":2,"tsn":26529},{"name":"Cardamine flexuosa","cnt":9,"tsn":22795},{"name":"Cardiospermum halicacabum","cnt":10,"tsn":28667},{"name":"Carduus crispus","cnt":7,"tsn":35786},{"name":"Carduus tenuiflorus","cnt":1,"tsn":35789},{"name":"Carex caryophyllea","cnt":1,"tsn":39542},{"name":"Carex distenta","cnt":1,"tsn":501213},{"name":"Carex divulsa","cnt":5,"tsn":501215},{"name":"Carex divulsa divulsa","cnt":3,"tsn":524893},{"name":"Carex pendula","cnt":1,"tsn":565047},{"name":"Carica papaya","cnt":3,"tsn":22324},{"name":"Catalpa ovata","cnt":15,"tsn":34314},{"name":"Caucalis platycarpos","cnt":3,"tsn":501336},{"name":"Celosia argentea","cnt":13,"tsn":20778},{"name":"Celtis australis","cnt":3,"tsn":565053},{"name":"Celtis sinensis","cnt":7,"tsn":897057},{"name":"Centaurea benedicta","cnt":2,"tsn":510524},{"name":"Centaurea calcitrapa","cnt":23,"tsn":36952},{"name":"Centaurea cineraria","cnt":1,"tsn":36953},{"name":"Centaurea diffusa","cnt":1,"tsn":36958},{"name":"Centaurea melitensis","cnt":1,"tsn":36965},{"name":"Centaurea montana","cnt":2,"tsn":36966},{"name":"Centaurea nigrescens","cnt":33,"tsn":36969},{"name":"Centaurea scabiosa","cnt":1,"tsn":36971},{"name":"Centaurea solstitialis","cnt":16,"tsn":36972},{"name":"Centaurea stoebe","cnt":159,"tsn":780246},{"name":"Centaurium erythraea","cnt":8,"tsn":30045},{"name":"Centaurium pulchellum","cnt":1,"tsn":822516},{"name":"Centranthus ruber","cnt":1,"tsn":35374},{"name":"Cerastium arvense arvense","cnt":2,"tsn":523822},{"name":"Cerastium brachypetalum","cnt":11,"tsn":19949},{"name":"Cerastium tomentosum","cnt":6,"tsn":19966},{"name":"Ceratotheca triloba","cnt":1,"tsn":34429},{"name":"Cercidiphyllum japonicum","cnt":4,"tsn":501368},{"name":"Cestrum nocturnum","cnt":1,"tsn":30498},{"name":"Chaenomeles japonica","cnt":3,"tsn":508021},{"name":"Chaerophyllum bulbosum","cnt":5,"tsn":29615},{"name":"Chaiturus marrubiastrum","cnt":26,"tsn":565058},{"name":"Chamaemelum nobile","cnt":1,"tsn":501396},{"name":"Chenopodium bonus-henricus","cnt":2,"tsn":20595},{"name":"Chenopodium ficifolium","cnt":2,"tsn":501483},{"name":"Chenopodium opulifolium","cnt":2,"tsn":20625},{"name":"Chenopodium polyspermum","cnt":6,"tsn":20628},{"name":"Chenopodium polyspermum acutifolium","cnt":1,"tsn":527327},{"name":"Chenopodium polyspermum obtusifolium","cnt":1,"tsn":527328},{"name":"Chenopodium urbicum","cnt":20,"tsn":20636},{"name":"Chenopodium vulvaria","cnt":7,"tsn":20637},{"name":"Chorispora tenella","cnt":4,"tsn":23099},{"name":"Chrysanthemum morifolium","cnt":3,"tsn":510898},{"name":"Cichorium endivia","cnt":3,"tsn":501522},{"name":"Cirsium palustre","cnt":1,"tsn":36394},{"name":"Citrullus lanatus lanatus","cnt":12,"tsn":527396},{"name":"Citrus aurantium","cnt":1,"tsn":825215},{"name":"Clematis viticella","cnt":1,"tsn":18719},{"name":"Clerodendrum trichotomum ferrugineum","cnt":1,"tsn":531017},{"name":"Coincya monensis recurvata","cnt":3,"tsn":524917},{"name":"Colubrina asiatica","cnt":1,"tsn":28521},{"name":"Commelina benghalensis","cnt":1,"tsn":39134},{"name":"Consolida regalis","cnt":3,"tsn":18762},{"name":"Conyza bonariensis","cnt":6,"tsn":37112},{"name":"Corchorus tridens","cnt":3,"tsn":506093},{"name":"Cornus kousa","cnt":2,"tsn":507498},{"name":"Cornus sanguinea","cnt":4,"tsn":501636},{"name":"Corrigiola litoralis","cnt":2,"tsn":20274},{"name":"Corynephorus canescens","cnt":1,"tsn":41599},{"name":"Cotoneaster apiculatus","cnt":3,"tsn":508023},{"name":"Cotoneaster simonsii","cnt":1,"tsn":501654},{"name":"Crataegus laevigata","cnt":1,"tsn":507255},{"name":"Crepis biennis","cnt":2,"tsn":37180},{"name":"Crepis setosa","cnt":3,"tsn":37211},{"name":"Crepis tectorum","cnt":6,"tsn":37212},{"name":"Crepis vesicaria","cnt":2,"tsn":37213},{"name":"Crinum asiaticum","cnt":1,"tsn":182711},{"name":"Crotalaria spectabilis","cnt":6,"tsn":26580},{"name":"Crypsis alopecuroides","cnt":1,"tsn":41603},{"name":"Cucumis melo","cnt":13,"tsn":22362},{"name":"Cucurbita maxima","cnt":3,"tsn":22369},{"name":"Cucurbita moschata","cnt":4,"tsn":22370},{"name":"Cucurbita pepo pepo","cnt":16,"tsn":527581},{"name":"Cuscuta epilinum","cnt":1,"tsn":30728},{"name":"Cuscuta epithymum","cnt":12,"tsn":30729},{"name":"Cuscuta japonica","cnt":3,"tsn":501850},{"name":"Cyclospermum leptophyllum","cnt":4,"tsn":507572},{"name":"Cynara cardunculus","cnt":1,"tsn":37221},{"name":"Cynoglossum amabile","cnt":1,"tsn":31886},{"name":"Cynosurus cristatus","cnt":12,"tsn":41624},{"name":"Cyperus amuricus","cnt":6,"tsn":39906},{"name":"Cyperus involucratus","cnt":1,"tsn":501929},{"name":"Cyperus rotundus","cnt":21,"tsn":39900},{"name":"Cyperus serotinus","cnt":1,"tsn":39964},{"name":"Cyrtomium falcatum","cnt":1,"tsn":17476},{"name":"Cyrtomium fortunei","cnt":1,"tsn":17477},{"name":"Cytisus scoparius scoparius","cnt":69,"tsn":527657},{"name":"Dactylis glomerata glomerata","cnt":1,"tsn":800049},{"name":"Dasypyrum villosum","cnt":1,"tsn":193450},{"name":"Delphinium elatum","cnt":2,"tsn":501978},{"name":"Dianthus deltoides","cnt":12,"tsn":20278},{"name":"Dicentra spectabilis","cnt":4,"tsn":502032},{"name":"Digitalis grandiflora","cnt":1,"tsn":502057},{"name":"Digitalis lanata","cnt":4,"tsn":33583},{"name":"Digitalis lutea","cnt":3,"tsn":33584},{"name":"Digitalis purpurea purpurea","cnt":7,"tsn":834205},{"name":"Dioscorea oppositifolia","cnt":123,"tsn":502075},{"name":"Diplotaxis muralis","cnt":9,"tsn":23118},{"name":"Diplotaxis tenuifolia","cnt":9,"tsn":502098},{"name":"Dipsacus","cnt":2,"tsn":35403},{"name":"Dipsacus sativus","cnt":5,"tsn":502099},{"name":"Dorstenia contrajerva","cnt":2,"tsn":19115},{"name":"Dysphania botrys","cnt":44,"tsn":822809},{"name":"Dysphania multifida","cnt":3,"tsn":822803},{"name":"Ecballium elaterium","cnt":1,"tsn":502196},{"name":"Echinochloa oryzoides","cnt":2,"tsn":502212},{"name":"Echinops ritro","cnt":1,"tsn":37287},{"name":"Echinops sphaerocephalus","cnt":5,"tsn":37290},{"name":"Echium plantagineum","cnt":1,"tsn":31898},{"name":"Echium pustulatum","cnt":1,"tsn":502218},{"name":"Eichhornia azurea","cnt":1,"tsn":42622},{"name":"Eichhornia crassipes","cnt":3,"tsn":42623},{"name":"Elaeagnus umbellata parvifolia","cnt":76,"tsn":527844},{"name":"Elsholtzia ciliata","cnt":3,"tsn":32493},{"name":"Emilia coccinea","cnt":1,"tsn":37303},{"name":"Ephedra distachya","cnt":1,"tsn":183500},{"name":"Epilobium parviflorum","cnt":1,"tsn":27321},{"name":"Eragrostis leptostachya","cnt":1,"tsn":502344},{"name":"Erica tetralix","cnt":2,"tsn":23650},{"name":"Erica vagans","cnt":1,"tsn":23651},{"name":"Eriochloa villosa","cnt":1,"tsn":41723},{"name":"Erodium cicutarium cicutarium","cnt":79,"tsn":524055},{"name":"Erodium moschatum","cnt":2,"tsn":29151},{"name":"Erodium moschatum moschatum","cnt":2,"tsn":528064},{"name":"Eruca vesicaria","cnt":4,"tsn":502429},{"name":"Eruca vesicaria sativa","cnt":4,"tsn":524057},{"name":"Eryngium foetidum","cnt":1,"tsn":29507},{"name":"Eryngium planum","cnt":1,"tsn":29501},{"name":"Erysimum cheiri","cnt":1,"tsn":22936},{"name":"Erysimum hieraciifolium","cnt":1,"tsn":502431},{"name":"Erythrostemon gilliesii","cnt":1,"tsn":820816},{"name":"Euonymus alatus alatus","cnt":5,"tsn":895068},{"name":"Euonymus fortunei radicans","cnt":7,"tsn":528151},{"name":"Euonymus hamiltonianus","cnt":2,"tsn":894989},{"name":"Euonymus hamiltonianus sieboldianus","cnt":2,"tsn":895058},{"name":"Euphorbia davidii","cnt":20,"tsn":565180},{"name":"Euphorbia exigua","cnt":3,"tsn":28065},{"name":"Euphorbia falcata","cnt":16,"tsn":28068},{"name":"Euphorbia lathyris","cnt":40,"tsn":1030645},{"name":"Euphorbia lucida","cnt":4,"tsn":28095},{"name":"Euphorbia peplus","cnt":24,"tsn":28117},{"name":"Euphorbia platyphyllos","cnt":2,"tsn":502547},{"name":"Euphorbia segetalis","cnt":3,"tsn":28132},{"name":"Euphrasia stricta","cnt":2,"tsn":502558},{"name":"Fagopyrum tataricum","cnt":4,"tsn":21283},{"name":"Fagus sylvatica","cnt":6,"tsn":502590},{"name":"Falcaria vulgaris","cnt":7,"tsn":29666},{"name":"Fallopia sachalinensis","cnt":2,"tsn":565898},{"name":"Fatoua villosa","cnt":4,"tsn":502591},{"name":"Ficus elastica","cnt":2,"tsn":19085},{"name":"Ficus pumila","cnt":7,"tsn":502618},{"name":"Filipendula ulmaria","cnt":12,"tsn":25171},{"name":"Fimbristylis littoralis","cnt":1,"tsn":507317},{"name":"Firmiana simplex","cnt":4,"tsn":21578},{"name":"Forsythia intermedia","cnt":3,"tsn":507912},{"name":"Fumaria parviflora","cnt":1,"tsn":18970},{"name":"Gaillardia grandiflora","cnt":7,"tsn":565203},{"name":"Galega officinalis","cnt":3,"tsn":26706},{"name":"Galeopsis bifida","cnt":45,"tsn":32496},{"name":"Galeopsis ladanum","cnt":3,"tsn":32497},{"name":"Galeopsis ladanum ladanum","cnt":3,"tsn":528205},{"name":"Galeopsis tetrahit","cnt":1,"tsn":32499},{"name":"Galinsoga urticifolia","cnt":2,"tsn":780342},{"name":"Galium divaricatum","cnt":31,"tsn":34851},{"name":"Galium odoratum","cnt":4,"tsn":502715},{"name":"Galium rubioides","cnt":1,"tsn":34911},{"name":"Galium tricornutum","cnt":3,"tsn":34932},{"name":"Galium verum verum","cnt":27,"tsn":846086},{"name":"Galium verum wirtgenii","cnt":3,"tsn":525800},{"name":"Galphimia gracilis","cnt":1,"tsn":29267},{"name":"Genista tinctoria","cnt":1,"tsn":26708},{"name":"Geranium pratense","cnt":1,"tsn":29114},{"name":"Geranium versicolor","cnt":4,"tsn":502766},{"name":"Gerbera jamesonii","cnt":1,"tsn":565210},{"name":"Geum urbanum","cnt":1,"tsn":24663},{"name":"Gladiolus gandavensis","cnt":10,"tsn":502781},{"name":"Glandularia hybrida","cnt":1,"tsn":508068},{"name":"Glaucium corniculatum","cnt":1,"tsn":502799},{"name":"Glebionis segetum","cnt":1,"tsn":780352},{"name":"Gomphrena globosa","cnt":10,"tsn":20804},{"name":"Grewia biloba","cnt":1,"tsn":507000},{"name":"Guizotia abyssinica","cnt":4,"tsn":37477},{"name":"Gypsophila muralis","cnt":3,"tsn":20292},{"name":"Hakonechloa macra","cnt":1,"tsn":783523},{"name":"Hedera hibernica","cnt":1,"tsn":822338},{"name":"Heliotropium amplexicaule","cnt":7,"tsn":31641},{"name":"Heliotropium arborescens","cnt":1,"tsn":502939},{"name":"Heliotropium indicum","cnt":5,"tsn":31638},{"name":"Heliotropium ramosissimum","cnt":1,"tsn":507685},{"name":"Heliotropium supinum","cnt":1,"tsn":502941},{"name":"Helleborus foetidus","cnt":2,"tsn":821153},{"name":"Helleborus niger","cnt":1,"tsn":195028},{"name":"Helleborus orientalis","cnt":4,"tsn":821155},{"name":"Helminthotheca echioides","cnt":1,"tsn":780367},{"name":"Hemarthria altissima","cnt":2,"tsn":41760},{"name":"Hemerocallis lilioasphodelus","cnt":16,"tsn":42944},{"name":"Hemigraphis alternata","cnt":1,"tsn":502943},{"name":"Heracleum sphondylium","cnt":1,"tsn":29671},{"name":"Heracleum sphondylium sibiricum","cnt":1,"tsn":524136},{"name":"Herniaria glabra","cnt":1,"tsn":20299},{"name":"Hibiscus schizopetalus","cnt":1,"tsn":21636},{"name":"Hieracium aurantiacum","cnt":70,"tsn":37697},{"name":"Hieracium murorum","cnt":3,"tsn":37717},{"name":"Hieracium sabaudum","cnt":8,"tsn":37726},{"name":"Hippocrepis comosa","cnt":1,"tsn":503043},{"name":"Holcus mollis","cnt":1,"tsn":41774},{"name":"Hordeum marinum","cnt":2,"tsn":40880},{"name":"Hordeum marinum gussoneanum","cnt":2,"tsn":797384},{"name":"Hordeum murinum","cnt":6,"tsn":40881},{"name":"Hordeum murinum glaucum","cnt":1,"tsn":524160},{"name":"Hordeum murinum murinum","cnt":1,"tsn":524162},{"name":"Hosta plantaginea","cnt":3,"tsn":42952},{"name":"Houttuynia cordata","cnt":2,"tsn":506518},{"name":"Humulus lupulus lupulus","cnt":2,"tsn":528498},{"name":"Hyacinthoides hispanica","cnt":1,"tsn":507012},{"name":"Hyacinthoides non-scripta","cnt":4,"tsn":810156},{"name":"Hyacinthus orientalis","cnt":5,"tsn":503095},{"name":"Hydrocharis morsus-ranae","cnt":1,"tsn":503098},{"name":"Hydrocleys nymphoides","cnt":4,"tsn":503099},{"name":"Hylotelephium erythrostictum","cnt":17,"tsn":565230},{"name":"Hylotelephium spectabile","cnt":3,"tsn":894365},{"name":"Hylotelephium telephium","cnt":58,"tsn":565233},{"name":"Hymenocallis littoralis","cnt":1,"tsn":507014},{"name":"Hyoscyamus albus","cnt":1,"tsn":503125},{"name":"Hypochaeris glabra","cnt":2,"tsn":37792},{"name":"Hyptis mutabilis","cnt":1,"tsn":32525},{"name":"Hyssopus officinalis","cnt":3,"tsn":32536},{"name":"Iberis sempervirens","cnt":2,"tsn":503151},{"name":"Iberis umbellata","cnt":6,"tsn":23145},{"name":"Ilex rotunda","cnt":2,"tsn":835358},{"name":"Impatiens balsamina","cnt":11,"tsn":29185},{"name":"Inula britannica","cnt":1,"tsn":503171},{"name":"Ipomoea batatas","cnt":6,"tsn":30764},{"name":"Ipomoea indica","cnt":14,"tsn":30775},{"name":"Ipomoea quamoclit","cnt":14,"tsn":30790},{"name":"Ipomoea tricolor","cnt":11,"tsn":30820},{"name":"Iris ensata","cnt":2,"tsn":503194},{"name":"Iris pallida","cnt":1,"tsn":43223},{"name":"Iris tectorum","cnt":2,"tsn":507025},{"name":"Isatis tinctoria","cnt":38,"tsn":23151},{"name":"Ixeris stolonifera","cnt":6,"tsn":503220},{"name":"Ixora coccinea","cnt":2,"tsn":35200},{"name":"Jacobaea vulgaris","cnt":1,"tsn":780394},{"name":"Jasione montana","cnt":3,"tsn":34582},{"name":"Jasminum multiflorum","cnt":1,"tsn":32972},{"name":"Jasminum officinale","cnt":3,"tsn":503238},{"name":"Jasminum sambac","cnt":1,"tsn":32970},{"name":"Jatropha integerrima","cnt":1,"tsn":28338},{"name":"Jatropha multifida","cnt":1,"tsn":28340},{"name":"Juncus inflexus","cnt":5,"tsn":39279},{"name":"Kickxia spuria","cnt":2,"tsn":33626},{"name":"Knautia arvensis","cnt":13,"tsn":35408},{"name":"Lablab purpureus","cnt":8,"tsn":503300},{"name":"Lactuca saligna","cnt":128,"tsn":36606},{"name":"Lactuca virosa","cnt":1,"tsn":503306},{"name":"Lagenaria siceraria","cnt":2,"tsn":22386},{"name":"Lamium purpureum incisum","cnt":1,"tsn":528670},{"name":"Lantana montevidensis","cnt":1,"tsn":32181},{"name":"Lappula marginata","cnt":1,"tsn":503328},{"name":"Larix kaempferi","cnt":4,"tsn":506606},{"name":"Lathyrus aphaca","cnt":1,"tsn":25838},{"name":"Lathyrus hirsutus","cnt":47,"tsn":25845},{"name":"Lathyrus sylvestris","cnt":1,"tsn":25881},{"name":"Lathyrus tuberosus","cnt":7,"tsn":25885},{"name":"Lavandula angustifolia","cnt":2,"tsn":503344},{"name":"Legousia speculum-veneris","cnt":2,"tsn":34586},{"name":"Lens culinaris","cnt":5,"tsn":503364},{"name":"Leonurus cardiaca cardiaca","cnt":148,"tsn":524220},{"name":"Leonurus sibiricus","cnt":3,"tsn":32550},{"name":"Lepidium graminifolium","cnt":1,"tsn":22964},{"name":"Lepidium heterophyllum","cnt":1,"tsn":22965},{"name":"Lepidium perfoliatum","cnt":4,"tsn":22974},{"name":"Lepidium ruderale","cnt":7,"tsn":22977},{"name":"Leucanthemum lacustre","cnt":1,"tsn":503420},{"name":"Leucanthemum superbum","cnt":1,"tsn":565274},{"name":"Leucojum aestivum","cnt":26,"tsn":503422},{"name":"Levisticum officinale","cnt":4,"tsn":29673},{"name":"Ligustrum amurense","cnt":7,"tsn":32974},{"name":"Ligustrum japonicum","cnt":6,"tsn":503449},{"name":"Ligustrum tschonoskii","cnt":2,"tsn":832825},{"name":"Lilium candidum","cnt":2,"tsn":503451},{"name":"Limonium sinuatum","cnt":1,"tsn":21336},{"name":"Linaria dalmatica","cnt":4,"tsn":503474},{"name":"Linaria dalmatica dalmatica","cnt":4,"tsn":524246},{"name":"Linaria genistifolia","cnt":1,"tsn":33217},{"name":"Linaria maroccana","cnt":2,"tsn":503475},{"name":"Linaria supina","cnt":1,"tsn":503481},{"name":"Linum bienne","cnt":6,"tsn":29233},{"name":"Linum catharticum","cnt":2,"tsn":29206},{"name":"Linum perenne","cnt":7,"tsn":29217},{"name":"Liriope muscari","cnt":4,"tsn":503501},{"name":"Lithospermum officinale","cnt":3,"tsn":31952},{"name":"Lobelia chinensis","cnt":2,"tsn":507722},{"name":"Lobelia erinus","cnt":2,"tsn":503509},{"name":"Logfia minima","cnt":1,"tsn":37958},{"name":"Lonicera notha","cnt":3,"tsn":503545},{"name":"Lonicera xylosteoides","cnt":1,"tsn":503549},{"name":"Luffa acutangula","cnt":1,"tsn":503569},{"name":"Luffa aegyptiaca","cnt":1,"tsn":503570},{"name":"Lunaria rediviva","cnt":2,"tsn":23239},{"name":"Luzula luzuloides","cnt":2,"tsn":39344},{"name":"Lycoris radiata","cnt":4,"tsn":503615},{"name":"Lythrum hyssopifolia","cnt":2,"tsn":27085},{"name":"Lythrum virgatum","cnt":1,"tsn":27089},{"name":"Macleaya cordata","cnt":18,"tsn":18976},{"name":"Magnolia kobus","cnt":2,"tsn":895295},{"name":"Magnolia stellata","cnt":1,"tsn":506192},{"name":"Malus hupehensis","cnt":2,"tsn":836454},{"name":"Malus purpurea","cnt":1,"tsn":836457},{"name":"Malus spectabilis","cnt":5,"tsn":836662},{"name":"Malus zumi","cnt":1,"tsn":516659},{"name":"Malva alcea","cnt":1,"tsn":21833},{"name":"Malva pusilla","cnt":5,"tsn":516667},{"name":"Malva verticillata","cnt":7,"tsn":21841},{"name":"Malvastrum coromandelianum","cnt":2,"tsn":503679},{"name":"Malvaviscus arboreus arboreus","cnt":1,"tsn":531406},{"name":"Marsilea mutica","cnt":3,"tsn":899182},{"name":"Matricaria chamomilla","cnt":3,"tsn":38074},{"name":"Mazus miquelii","cnt":10,"tsn":503714},{"name":"Medicago arabica","cnt":4,"tsn":503718},{"name":"Medicago minima","cnt":5,"tsn":503722},{"name":"Medicago polymorpha","cnt":4,"tsn":503725},{"name":"Medicago sativa sativa","cnt":36,"tsn":524303},{"name":"Melia azedarach","cnt":23,"tsn":29024},{"name":"Melilotus altissimus","cnt":5,"tsn":503739},{"name":"Melilotus indicus","cnt":1,"tsn":503741},{"name":"Melilotus sulcatus","cnt":1,"tsn":503743},{"name":"Mentha verticillata","cnt":11,"tsn":32276},{"name":"Mentha villosa","cnt":7,"tsn":503754},{"name":"Mesembryanthemum crystallinum","cnt":1,"tsn":503818},{"name":"Metasequoia glyptostroboides","cnt":5,"tsn":505864},{"name":"Milium vernale","cnt":5,"tsn":503831},{"name":"Mimosa pudica","cnt":1,"tsn":26790},{"name":"Miscanthus floridulus","cnt":1,"tsn":41871},{"name":"Misopates orontium","cnt":3,"tsn":503855},{"name":"Mollugo cerviana","cnt":1,"tsn":19900},{"name":"Momordica charantia","cnt":2,"tsn":22399},{"name":"Moricandia arvensis","cnt":1,"tsn":503873},{"name":"Moringa oleifera","cnt":1,"tsn":503874},{"name":"Morus nigra","cnt":1,"tsn":19069},{"name":"Mosla dianthera","cnt":1,"tsn":32621},{"name":"Musa acuminata","cnt":2,"tsn":42390},{"name":"Muscari armeniacum","cnt":2,"tsn":503891},{"name":"Muscari comosum","cnt":6,"tsn":42978},{"name":"Myosotis sylvatica","cnt":5,"tsn":31698},{"name":"Nasturtium microphyllum","cnt":5,"tsn":23254},{"name":"Nelumbo nucifera","cnt":1,"tsn":18400},{"name":"Nerium oleander","cnt":2,"tsn":30184},{"name":"Neslia paniculata","cnt":1,"tsn":23261},{"name":"Nicotiana alata","cnt":1,"tsn":503954},{"name":"Nicotiana longiflora","cnt":5,"tsn":30575},{"name":"Nicotiana rustica","cnt":1,"tsn":30566},{"name":"Nicotiana tabacum","cnt":3,"tsn":30568},{"name":"Nigella damascena","cnt":11,"tsn":18793},{"name":"Nipponanthemum nipponicum","cnt":1,"tsn":780461},{"name":"Nonea rosea","cnt":1,"tsn":31961},{"name":"Nonea vesicaria","cnt":1,"tsn":503962},{"name":"Nothoscordum borbonicum","cnt":2,"tsn":565322},{"name":"Nymphoides peltata","cnt":5,"tsn":29998},{"name":"Oenanthe aquatica","cnt":2,"tsn":29564},{"name":"Oenanthe pimpinelloides","cnt":1,"tsn":503993},{"name":"Oenothera glazioviana","cnt":3,"tsn":27401},{"name":"Ononis spinosa","cnt":1,"tsn":26813},{"name":"Opuntia ficus-indica","cnt":3,"tsn":19706},{"name":"Origanum majorana","cnt":2,"tsn":32631},{"name":"Ornithopus perpusillus","cnt":2,"tsn":504060},{"name":"Orobanche ramosa","cnt":1,"tsn":34298},{"name":"Pachysandra terminalis","cnt":21,"tsn":504090},{"name":"Panicum antidotale","cnt":1,"tsn":504098},{"name":"Panicum bisulcatum","cnt":1,"tsn":504099},{"name":"Papaver argemone","cnt":2,"tsn":504109},{"name":"Papaver hybridum","cnt":1,"tsn":18890},{"name":"Papaver orientale","cnt":5,"tsn":18892},{"name":"Papaver rhoeas","cnt":18,"tsn":18893},{"name":"Papaver somniferum","cnt":16,"tsn":18894},{"name":"Parietaria judaica","cnt":1,"tsn":19167},{"name":"Parthenium hysterophorus","cnt":6,"tsn":38164},{"name":"Paspalum urvillei","cnt":6,"tsn":41043},{"name":"Passiflora caerulea","cnt":1,"tsn":22245},{"name":"Passiflora coccinea","cnt":1,"tsn":22222},{"name":"Periploca graeca","cnt":5,"tsn":30399},{"name":"Persicaria posumbu","cnt":1,"tsn":823794},{"name":"Petasites hybridus","cnt":1,"tsn":36056},{"name":"Petrorhagia saxifraga","cnt":5,"tsn":504265},{"name":"Peucedanum ostruthium","cnt":6,"tsn":29819},{"name":"Phaseolus coccineus","cnt":2,"tsn":26845},{"name":"Phaseolus lunatus","cnt":1,"tsn":26850},{"name":"Phaseolus vulgaris","cnt":1,"tsn":26857},{"name":"Phedimus aizoon","cnt":4,"tsn":894346},{"name":"Phedimus spurius","cnt":5,"tsn":894339},{"name":"Photinia glabra","cnt":1,"tsn":565396},{"name":"Photinia serratifolia","cnt":1,"tsn":507109},{"name":"Photinia villosa","cnt":5,"tsn":504347},{"name":"Phyllanthus urinaria","cnt":1,"tsn":28381},{"name":"Phyllostachys aureosulcata","cnt":9,"tsn":504356},{"name":"Physalis alkekengi","cnt":19,"tsn":30589},{"name":"Physalis philadelphica","cnt":9,"tsn":504374},{"name":"Physalis philadelphica immaculata","cnt":7,"tsn":529632},{"name":"Pimpinella major","cnt":1,"tsn":29823},{"name":"Pimpinella saxifraga saxifraga","cnt":19,"tsn":29825},{"name":"Pinellia ternata","cnt":5,"tsn":42551},{"name":"Pisum sativum","cnt":9,"tsn":26867},{"name":"Pithecoctenium crucigerum","cnt":1,"tsn":565411},{"name":"Plantago coronopus","cnt":1,"tsn":32903},{"name":"Plantago media","cnt":3,"tsn":32888},{"name":"Plantago psyllium","cnt":7,"tsn":32908},{"name":"Platycodon grandiflorus","cnt":5,"tsn":845355},{"name":"Plectranthus parviflorus","cnt":18,"tsn":32830},{"name":"Plumbago auriculata","cnt":1,"tsn":504462},{"name":"Poa pratensis pratensis","cnt":185,"tsn":802227},{"name":"Podocarpus macrophyllus","cnt":1,"tsn":183490},{"name":"Polemonium caeruleum","cnt":2,"tsn":31005},{"name":"Polycarpon tetraphyllum","cnt":2,"tsn":504491},{"name":"Polycarpon tetraphyllum tetraphyllum","cnt":2,"tsn":566073},{"name":"Polygonum aviculare depressum","cnt":1,"tsn":823866},{"name":"Polygonum bellardii","cnt":12,"tsn":565424},{"name":"Populus nigra","cnt":44,"tsn":22468},{"name":"Portulaca amilis","cnt":2,"tsn":504539},{"name":"Potentilla anglica","cnt":1,"tsn":24684},{"name":"Potentilla argentea","cnt":86,"tsn":24691},{"name":"Prunus domestica","cnt":14,"tsn":24774},{"name":"Prunus padus","cnt":9,"tsn":24798},{"name":"Prunus spinosa","cnt":6,"tsn":24802},{"name":"Prunus triloba","cnt":6,"tsn":504628},{"name":"Pteris multifida","cnt":5,"tsn":17704},{"name":"Pteris vittata","cnt":1,"tsn":17706},{"name":"Pterocarya stenoptera","cnt":2,"tsn":504666},{"name":"Puccinellia distans distans","cnt":14,"tsn":802275},{"name":"Puccinellia rupestris","cnt":3,"tsn":41223},{"name":"Pyracantha crenulata","cnt":2,"tsn":565446},{"name":"Pyrus pyrifolia","cnt":15,"tsn":25296},{"name":"Quercus cerris","cnt":6,"tsn":506534},{"name":"Quercus robur","cnt":27,"tsn":19405},{"name":"Ranunculus arvensis","cnt":4,"tsn":18592},{"name":"Rapistrum rugosum","cnt":2,"tsn":23292},{"name":"Reseda alba","cnt":3,"tsn":504737},{"name":"Reseda luteola","cnt":3,"tsn":504738},{"name":"Reseda phyteuma","cnt":1,"tsn":504740},{"name":"Rhamnus cathartica","cnt":24,"tsn":28573},{"name":"Rhamnus davurica","cnt":4,"tsn":28578},{"name":"Rheum rhabarbarum","cnt":8,"tsn":504747},{"name":"Ricinus communis","cnt":9,"tsn":28393},{"name":"Rorippa amphibia","cnt":1,"tsn":22994},{"name":"Rorippa austriaca","cnt":3,"tsn":22995},{"name":"Rosa bracteata","cnt":5,"tsn":24817},{"name":"Rosa centifolia","cnt":4,"tsn":836519},{"name":"Rosa chinensis","cnt":1,"tsn":24821},{"name":"Rosa laevigata","cnt":1,"tsn":24830},{"name":"Rosa majalis","cnt":1,"tsn":504822},{"name":"Rosa rubiginosa","cnt":63,"tsn":520258},{"name":"Rosa rubiginosa nemoralis","cnt":2,"tsn":837384},{"name":"Rosa spinosissima","cnt":2,"tsn":24840},{"name":"Rosmarinus officinalis","cnt":1,"tsn":32677},{"name":"Rostraria cristata","cnt":1,"tsn":504835},{"name":"Rubia tinctorum","cnt":1,"tsn":35145},{"name":"Rubus parvifolius","cnt":1,"tsn":836780},{"name":"Rumex conglomeratus","cnt":48,"tsn":20936},{"name":"Rumex sanguineus","cnt":3,"tsn":20975},{"name":"Russelia equisetiformis","cnt":1,"tsn":34023},{"name":"Ruta graveolens","cnt":20,"tsn":29002},{"name":"Sagina japonica","cnt":4,"tsn":20025},{"name":"Salix alba","cnt":103,"tsn":565478},{"name":"Salix matsudana","cnt":6,"tsn":504971},{"name":"Salix pendulina","cnt":4,"tsn":507155},{"name":"Salix purpurea","cnt":46,"tsn":22574},{"name":"Salpichroa origanifolia","cnt":4,"tsn":821257},{"name":"Salsola collina","cnt":1,"tsn":20656},{"name":"Salsola tragus","cnt":32,"tsn":520950},{"name":"Salvia argentea","cnt":1,"tsn":504991},{"name":"Salvia pratensis","cnt":6,"tsn":32735},{"name":"Salvia sclarea","cnt":4,"tsn":32741},{"name":"Salvia splendens","cnt":6,"tsn":32745},{"name":"Salvia verbenaca","cnt":2,"tsn":832901},{"name":"Salvia verticillata","cnt":8,"tsn":32752},{"name":"Salvinia molesta","cnt":3,"tsn":181823},{"name":"Samolus valerandi","cnt":75,"tsn":504999},{"name":"Saponaria ocymoides","cnt":2,"tsn":505008},{"name":"Satureja hortensis","cnt":9,"tsn":32308},{"name":"Satureja montana","cnt":1,"tsn":505016},{"name":"Scandix pecten-veneris","cnt":4,"tsn":29865},{"name":"Scolymus hispanicus","cnt":1,"tsn":505088},{"name":"Scorpiurus muricatus","cnt":2,"tsn":26946},{"name":"Scrophularia umbrosa","cnt":1,"tsn":505095},{"name":"Sedum acre","cnt":31,"tsn":24105},{"name":"Sedum album","cnt":6,"tsn":24108},{"name":"Senecio sylvaticus","cnt":2,"tsn":505138},{"name":"Senecio viscosus","cnt":13,"tsn":36193},{"name":"Senna occidentalis","cnt":2,"tsn":505166},{"name":"Sesamum indicum","cnt":1,"tsn":34431},{"name":"Sesbania punicea","cnt":1,"tsn":26954},{"name":"Setaria adhaerens","cnt":1,"tsn":521410},{"name":"Setaria verticilliformis","cnt":2,"tsn":795068},{"name":"Sida linifolia","cnt":1,"tsn":21730},{"name":"Sideritis romana","cnt":1,"tsn":32759},{"name":"Silene coronaria","cnt":4,"tsn":521498},{"name":"Silene csereii","cnt":10,"tsn":505229},{"name":"Silene flos-cuculi","cnt":1,"tsn":521501},{"name":"Silene gallica","cnt":4,"tsn":20067},{"name":"Silybum marianum","cnt":8,"tsn":38413},{"name":"Sisymbrium irio","cnt":1,"tsn":23314},{"name":"Sisymbrium loeselii","cnt":1,"tsn":23315},{"name":"Solanum sisymbriifolium","cnt":1,"tsn":30457},{"name":"Solanum tuberosum","cnt":12,"tsn":505272},{"name":"Soliva sessilis","cnt":1,"tsn":38879},{"name":"Sonchus arvensis arvensis","cnt":20,"tsn":38422},{"name":"Sonchus arvensis uliginosus","cnt":68,"tsn":38423},{"name":"Sorbus aucuparia","cnt":15,"tsn":25320},{"name":"Sorbus hybrida","cnt":1,"tsn":505297},{"name":"Sparganium emersum","cnt":38,"tsn":42315},{"name":"Spergula pentandra","cnt":4,"tsn":20366},{"name":"Sphagneticola trilobata","cnt":2,"tsn":565537},{"name":"Spinacia oleracea","cnt":1,"tsn":20709},{"name":"Spiraea japonica fortunei","cnt":49,"tsn":530519},{"name":"Spiraea salicifolia","cnt":4,"tsn":25339},{"name":"Spiraea trilobata","cnt":4,"tsn":505339},{"name":"Stachys annua","cnt":1,"tsn":32313},{"name":"Stachys arvensis","cnt":2,"tsn":32326},{"name":"Stachys germanica","cnt":6,"tsn":32339},{"name":"Stachys recta","cnt":2,"tsn":32315},{"name":"Stachys sylvatica","cnt":1,"tsn":32322},{"name":"Stellaria holostea","cnt":3,"tsn":20182},{"name":"Sternbergia lutea","cnt":1,"tsn":507188},{"name":"Styphnolobium japonicum","cnt":2,"tsn":820265},{"name":"Styrax japonicus","cnt":4,"tsn":505974},{"name":"Succisella inflexa","cnt":4,"tsn":505405},{"name":"Symplocos paniculata","cnt":5,"tsn":897474},{"name":"Syringa josikaea","cnt":1,"tsn":565556},{"name":"Syringa pekinensis","cnt":1,"tsn":565840},{"name":"Taeniatherum caput-medusae","cnt":1,"tsn":42203},{"name":"Tagetes minuta","cnt":7,"tsn":38487},{"name":"Tamarix gallica","cnt":1,"tsn":22304},{"name":"Tamarix ramosissima","cnt":1,"tsn":22310},{"name":"Tanacetum balsamita","cnt":5,"tsn":36323},{"name":"Taxus baccata","cnt":9,"tsn":194883},{"name":"Tecoma capensis","cnt":1,"tsn":505435},{"name":"Tetradium daniellii","cnt":2,"tsn":825211},{"name":"Tetragonia tetragonioides","cnt":7,"tsn":19938},{"name":"Teucrium botrys","cnt":4,"tsn":32353},{"name":"Thinopyrum pycnanthum","cnt":1,"tsn":565567},{"name":"Thymus praecox","cnt":4,"tsn":32821},{"name":"Thymus praecox arcticus","cnt":6,"tsn":524754},{"name":"Thymus pulegioides","cnt":21,"tsn":505500},{"name":"Tilia europaea","cnt":6,"tsn":522582},{"name":"Tithonia rotundifolia","cnt":3,"tsn":38532},{"name":"Torilis arvensis arvensis","cnt":21,"tsn":566105},{"name":"Torilis japonica","cnt":15,"tsn":29895},{"name":"Torilis leptophylla","cnt":1,"tsn":505535},{"name":"Tradescantia spathacea","cnt":3,"tsn":505554},{"name":"Tragopogon porrifolius","cnt":52,"tsn":38568},{"name":"Tricyrtis hirta","cnt":1,"tsn":505579},{"name":"Trifolium alexandrinum","cnt":1,"tsn":26210},{"name":"Trifolium fragiferum","cnt":1,"tsn":26251},{"name":"Trifolium lappaceum","cnt":1,"tsn":26266},{"name":"Trifolium resupinatum","cnt":10,"tsn":26316},{"name":"Trifolium squamosum","cnt":2,"tsn":505584},{"name":"Trifolium stellatum","cnt":1,"tsn":820259},{"name":"Trifolium striatum","cnt":1,"tsn":26320},{"name":"Trigonella procumbens","cnt":2,"tsn":505591},{"name":"Tripolium pannonicum","cnt":1,"tsn":565581},{"name":"Tristagma uniflorum","cnt":9,"tsn":565582},{"name":"Tulipa sylvestris","cnt":7,"tsn":43106},{"name":"Turgenia latifolia","cnt":1,"tsn":29901},{"name":"Ulex europaeus","cnt":4,"tsn":27013},{"name":"Ulmus pumila","cnt":25,"tsn":19057},{"name":"Urochloa ramosa","cnt":4,"tsn":523031},{"name":"Urtica dioica dioica","cnt":37,"tsn":19153},{"name":"Urtica urens","cnt":5,"tsn":19158},{"name":"Vaccaria hispanica","cnt":34,"tsn":505628},{"name":"Verbascum nigrum","cnt":1,"tsn":505651},{"name":"Verbascum phoeniceum","cnt":1,"tsn":505652},{"name":"Verbascum virgatum","cnt":2,"tsn":33395},{"name":"Verbena bonariensis","cnt":2,"tsn":32128},{"name":"Verbena brasiliensis","cnt":16,"tsn":32086},{"name":"Verbena officinalis officinalis","cnt":19,"tsn":531138},{"name":"Verbena rigida","cnt":2,"tsn":32118},{"name":"Veronica austriaca","cnt":5,"tsn":505667},{"name":"Veronica beccabunga","cnt":7,"tsn":33412},{"name":"Veronica dillenii","cnt":1,"tsn":33416},{"name":"Veronica officinalis officinalis","cnt":192,"tsn":530795},{"name":"Veronica spicata","cnt":1,"tsn":505675},{"name":"Viburnum lantana","cnt":16,"tsn":35264},{"name":"Viburnum opulus opulus","cnt":2,"tsn":531140},{"name":"Viburnum rhytidophyllum","cnt":4,"tsn":505679},{"name":"Viburnum setigerum","cnt":4,"tsn":565596},{"name":"Viburnum tinus","cnt":1,"tsn":505680},{"name":"Vicia sativa nigra","cnt":30,"tsn":541686},{"name":"Vicia sepium","cnt":2,"tsn":26357},{"name":"Vicia sepium sepium","cnt":2,"tsn":530813},{"name":"Vigna radiata","cnt":1,"tsn":506804},{"name":"Viola patrinii","cnt":1,"tsn":565599},{"name":"Vitex agnus-castus agnus-castus","cnt":7,"tsn":531143},{"name":"Vitis vinifera","cnt":9,"tsn":28629},{"name":"Vulpia ciliata","cnt":1,"tsn":505733},{"name":"Weigela florida","cnt":2,"tsn":505745},{"name":"Wisteria formosa","cnt":1,"tsn":505747},{"name":"Zephyranthes candida","cnt":2,"tsn":505793},{"name":"Zephyranthes rosea","cnt":1,"tsn":505800},{"name":"Zinnia angustifolia","cnt":1,"tsn":507678},{"name":"Zinnia violacea","cnt":6,"tsn":505806},{"name":"Zoysia matrella","cnt":2,"tsn":42274},{"name":"Zygophyllum fabago","cnt":1,"tsn":29059}]}
